gepo/__init__.py
gepo/gepo.py
gepo-0.1.1.dist-info/LICENSE
gepo-0.1.1.dist-info/METADATA
gepo-0.1.1.dist-info/WHEEL
gepo-0.1.1.dist-info/entry_points.txt
gepo-0.1.1.dist-info/top_level.txt
gepo-0.1.1.dist-info/RECORD
