Metadata-Version: 2.1
Name: gepo
Version: 0.1.1
Summary: gepo [GEtPOst] is a powerful, easy-to-use command-line tool for making HTTP requests. Built for developers, testers, and API enthusiasts.
Home-page: https://github.com/baltej223/gepo
Author: Baltej
Author-email: baltej_s@outlook.com
Classifier: Programming Language :: Python :: 3
Classifier: License :: OSI Approved :: MIT License
Classifier: Operating System :: OS Independent
Requires-Python: >=3.6
License-File: LICENSE
